{
  "name": "just",
  "word": "identifier",
  "rules": {
    "file": {
      "type": "REPEAT",
      "content": {
        "type": "CHOICE",
        "members": [
          {
            "type": "SYMBOL",
            "name": "alias"
          },
          {
            "type": "SYMBOL",
            "name": "string"
          },
          {
            "type": "SYMBOL",
            "name": "setting"
          },
          {
            "type": "SYMBOL",
            "name": "identifier"
          }
        ]
      }
    },
    "setting": {
      "type": "SEQ",
      "members": [
        {
          "type": "STRING",
          "value": "set"
        },
        {
          "type": "CHOICE",
          "members": [
            {
              "type": "SEQ",
              "members": [
                {
                  "type": "STRING",
                  "value": "allow-duplicate-recipes"
                },
                {
                  "type": "CHOICE",
                  "members": [
                    {
                      "type": "SEQ",
                      "members": [
                        {
                          "type": "STRING",
                          "value": ":="
                        },
                        {
                          "type": "SYMBOL",
                          "name": "boolean"
                        }
                      ]
                    },
                    {
                      "type": "BLANK"
                    }
                  ]
                }
              ]
            },
            {
              "type": "SEQ",
              "members": [
                {
                  "type": "STRING",
                  "value": "allow-duplicate-variables"
                },
                {
                  "type": "CHOICE",
                  "members": [
                    {
                      "type": "SEQ",
                      "members": [
                        {
                          "type": "STRING",
                          "value": ":="
                        },
                        {
                          "type": "SYMBOL",
                          "name": "boolean"
                        }
                      ]
                    },
                    {
                      "type": "BLANK"
                    }
                  ]
                }
              ]
            },
            {
              "type": "SEQ",
              "members": [
                {
                  "type": "STRING",
                  "value": "dotenv-filename"
                },
                {
                  "type": "STRING",
                  "value": ":="
                },
                {
                  "type": "SYMBOL",
                  "name": "string"
                }
              ]
            }
          ]
        }
      ]
    },
    "alias": {
      "type": "SEQ",
      "members": [
        {
          "type": "STRING",
          "value": "alias"
        },
        {
          "type": "SYMBOL",
          "name": "identifier"
        },
        {
          "type": "STRING",
          "value": ":="
        },
        {
          "type": "SYMBOL",
          "name": "identifier"
        }
      ]
    },
    "string": {
      "type": "CHOICE",
      "members": [
        {
          "type": "SYMBOL",
          "name": "indented_normal_string"
        },
        {
          "type": "SYMBOL",
          "name": "normal_string"
        },
        {
          "type": "SYMBOL",
          "name": "indented_raw_string"
        },
        {
          "type": "SYMBOL",
          "name": "raw_string"
        }
      ]
    },
    "indented_normal_string": {
      "type": "SEQ",
      "members": [
        {
          "type": "STRING",
          "value": "\"\"\""
        },
        {
          "type": "REPEAT",
          "content": {
            "type": "CHOICE",
            "members": [
              {
                "type": "SYMBOL",
                "name": "escape_sequence"
              },
              {
                "type": "PATTERN",
                "value": ".[^\"]?"
              }
            ]
          }
        },
        {
          "type": "STRING",
          "value": "\"\"\""
        }
      ]
    },
    "normal_string": {
      "type": "SEQ",
      "members": [
        {
          "type": "STRING",
          "value": "\""
        },
        {
          "type": "REPEAT",
          "content": {
            "type": "CHOICE",
            "members": [
              {
                "type": "SYMBOL",
                "name": "escape_sequence"
              },
              {
                "type": "PATTERN",
                "value": "[^\"]"
              }
            ]
          }
        },
        {
          "type": "STRING",
          "value": "\""
        }
      ]
    },
    "indented_raw_string": {
      "type": "SEQ",
      "members": [
        {
          "type": "STRING",
          "value": "'''"
        },
        {
          "type": "REPEAT",
          "content": {
            "type": "PATTERN",
            "value": ".[^']?"
          }
        },
        {
          "type": "STRING",
          "value": "'''"
        }
      ]
    },
    "raw_string": {
      "type": "SEQ",
      "members": [
        {
          "type": "STRING",
          "value": "'"
        },
        {
          "type": "PATTERN",
          "value": "[^']*"
        },
        {
          "type": "STRING",
          "value": "'"
        }
      ]
    },
    "escape_sequence": {
      "type": "CHOICE",
      "members": [
        {
          "type": "STRING",
          "value": "\\n"
        },
        {
          "type": "STRING",
          "value": "\\r"
        },
        {
          "type": "STRING",
          "value": "\\t"
        },
        {
          "type": "STRING",
          "value": "\\\""
        },
        {
          "type": "STRING",
          "value": "\\\\"
        }
      ]
    },
    "boolean": {
      "type": "CHOICE",
      "members": [
        {
          "type": "STRING",
          "value": "true"
        },
        {
          "type": "STRING",
          "value": "false"
        }
      ]
    },
    "identifier": {
      "type": "PATTERN",
      "value": "[a-zA-Z_][a-zA-Z0-9_-]*"
    },
    "comment": {
      "type": "PREC",
      "value": -1,
      "content": {
        "type": "TOKEN",
        "content": {
          "type": "SEQ",
          "members": [
            {
              "type": "STRING",
              "value": "#"
            },
            {
              "type": "PATTERN",
              "value": ".*"
            }
          ]
        }
      }
    }
  },
  "extras": [
    {
      "type": "PATTERN",
      "value": "\\s"
    },
    {
      "type": "SYMBOL",
      "name": "comment"
    }
  ],
  "conflicts": [],
  "precedences": [],
  "externals": [],
  "inline": [],
  "supertypes": []
}
